django_robokassa-1.3.dist-info/DESCRIPTION.rst
django_robokassa-1.3.dist-info/METADATA
django_robokassa-1.3.dist-info/metadata.json
django_robokassa-1.3.dist-info/pbr.json
django_robokassa-1.3.dist-info/RECORD
django_robokassa-1.3.dist-info/top_level.txt
django_robokassa-1.3.dist-info/WHEEL
robokassa/__init__.py
robokassa/conf.py
robokassa/forms.py
robokassa/models.py
robokassa/signals.py
robokassa/tests.py
robokassa/urls.py
robokassa/views.py
robokassa/migrations/0001_initial.py
robokassa/migrations/0002_update_to_14.py
robokassa/migrations/__init__.py
